fds/__init__.py
fds/sdk/__init__.py
fds/sdk/SecuritizedDerivativesAPIforDigitalPortals/__init__.py
fds/sdk/SecuritizedDerivativesAPIforDigitalPortals/api_client.py
fds/sdk/SecuritizedDerivativesAPIforDigitalPortals/configuration.py
fds/sdk/SecuritizedDerivativesAPIforDigitalPortals/exceptions.py
fds/sdk/SecuritizedDerivativesAPIforDigitalPortals/model_utils.py
fds/sdk/SecuritizedDerivativesAPIforDigitalPortals/rest.py
fds/sdk/SecuritizedDerivativesAPIforDigitalPortals/api/__init__.py
fds/sdk/SecuritizedDerivativesAPIforDigitalPortals/api/securitized_derivative_api.py
fds/sdk/SecuritizedDerivativesAPIforDigitalPortals/apis/__init__.py
fds/sdk/SecuritizedDerivativesAPIforDigitalPortals/model/__init__.py
fds/sdk/SecuritizedDerivativesAPIforDigitalPortals/model/attributes_member.py
fds/sdk/SecuritizedDerivativesAPIforDigitalPortals/model/get_securitized_derivative_barrier_type_list_data_items.py
fds/sdk/SecuritizedDerivativesAPIforDigitalPortals/model/get_securitized_derivative_get_data_country_security_registration_items.py
fds/sdk/SecuritizedDerivativesAPIforDigitalPortals/model/get_securitized_derivative_get_data_type_items.py
fds/sdk/SecuritizedDerivativesAPIforDigitalPortals/model/get_securitized_derivative_key_figures_notation_get_data_underlyings_items.py
fds/sdk/SecuritizedDerivativesAPIforDigitalPortals/model/get_securitized_derivative_key_figures_notation_get_data_underlyings_items_level.py
fds/sdk/SecuritizedDerivativesAPIforDigitalPortals/model/get_securitized_derivative_key_figures_notation_get_data_underlyings_items_notation.py
fds/sdk/SecuritizedDerivativesAPIforDigitalPortals/model/get_securitized_derivative_key_figures_notation_get_data_underlyings_items_notation_instrument.py
fds/sdk/SecuritizedDerivativesAPIforDigitalPortals/model/get_securitized_derivative_key_figures_notation_get_data_underlyings_items_value_unit.py
fds.sdk.SecuritizedDerivativesAPIforDigitalPortals-0.40.1.dist-info/LICENSE
fds.sdk.SecuritizedDerivativesAPIforDigitalPortals-0.40.1.dist-info/METADATA
fds.sdk.SecuritizedDerivativesAPIforDigitalPortals-0.40.1.dist-info/WHEEL
fds.sdk.SecuritizedDerivativesAPIforDigitalPortals-0.40.1.dist-info/top_level.txt
fds.sdk.SecuritizedDerivativesAPIforDigitalPortals-0.40.1.dist-info/RECORD
